{"nodes": [{"id": "dep_prop_propagation_engine", "label": "Dependency Propagation Engine", "file_type": "rationale", "source_file": "docs/architecture/dependency-propagation.md", "source_location": null, "source_url": null, "captured_at": null, "author": null, "contributor": null}, {"id": "dep_prop_staleness", "label": "Node Staleness Mechanism", "file_type": "rationale", "source_file": "docs/architecture/dependency-propagation.md", "source_location": null, "source_url": null, "captured_at": null, "author": null, "contributor": null}, {"id": "dep_prop_invalidation_cascade", "label": "Invalidation Cascade", "file_type": "rationale", "source_file": "docs/architecture/dependency-propagation.md", "source_location": null, "source_url": null, "captured_at": null, "author": null, "contributor": null}, {"id": "dep_prop_recalculation", "label": "Recalculation Model", "file_type": "rationale", "source_file": "docs/architecture/dependency-propagation.md", "source_location": null, "source_url": null, "captured_at": null, "author": null, "contributor": null}, {"id": "dep_prop_propagation_boundaries", "label": "Propagation Boundaries (Hard and Soft)", "file_type": "rationale", "source_file": "docs/architecture/dependency-propagation.md", "source_location": null, "source_url": null, "captured_at": null, "author": null, "contributor": null}, {"id": "dep_prop_cycle_detection", "label": "Cycle Detection (DAG Enforcement)", "file_type": "rationale", "source_file": "docs/architecture/dependency-propagation.md", "source_location": null, "source_url": null, "captured_at": null, "author": null, "contributor": null}, {"id": "dep_prop_batch_propagation", "label": "Batch Propagation Semantics", "file_type": "rationale", "source_file": "docs/architecture/dependency-propagation.md", "source_location": null, "source_url": null, "captured_at": null, "author": null, "contributor": null}, {"id": "dep_prop_downstream_propagation", "label": "Downstream Propagation (Forward Traversal)", "file_type": "rationale", "source_file": "docs/architecture/dependency-propagation.md", "source_location": null, "source_url": null, "captured_at": null, "author": null, "contributor": null}, {"id": "dep_prop_upstream_traversal", "label": "Upstream Traversal (Reverse Traversal)", "file_type": "rationale", "source_file": "docs/architecture/dependency-propagation.md", "source_location": null, "source_url": null, "captured_at": null, "author": null, "contributor": null}, {"id": "dep_prop_typed_edge_ref", "label": "Typed Edge Semantics (referenced by Dependency Propagation)", "file_type": "document", "source_file": "docs/architecture/dependency-propagation.md", "source_location": null, "source_url": null, "captured_at": null, "author": null, "contributor": null}, {"id": "dep_prop_adr004_ref", "label": "ADR-004 Event-Driven Communication (referenced by Dep. Propagation)", "file_type": "document", "source_file": "docs/architecture/dependency-propagation.md", "source_location": null, "source_url": null, "captured_at": null, "author": null, "contributor": null}], "edges": [{"source": "dep_prop_propagation_engine", "target": "dep_prop_staleness", "relation": "conceptually_related_to", "confidence": "EXTRACTED", "confidence_score": 1.0, "source_file": "docs/architecture/dependency-propagation.md", "source_location": "Core Concept section", "weight": 1.0}, {"source": "dep_prop_propagation_engine", "target": "dep_prop_invalidation_cascade", "relation": "conceptually_related_to", "confidence": "EXTRACTED", "confidence_score": 1.0, "source_file": "docs/architecture/dependency-propagation.md", "source_location": "Invalidation Cascade section", "weight": 1.0}, {"source": "dep_prop_propagation_engine", "target": "dep_prop_recalculation", "relation": "conceptually_related_to", "confidence": "EXTRACTED", "confidence_score": 1.0, "source_file": "docs/architecture/dependency-propagation.md", "source_location": "Recalculation section", "weight": 1.0}, {"source": "dep_prop_propagation_engine", "target": "dep_prop_propagation_boundaries", "relation": "conceptually_related_to", "confidence": "EXTRACTED", "confidence_score": 1.0, "source_file": "docs/architecture/dependency-propagation.md", "source_location": "Propagation Boundaries section", "weight": 1.0}, {"source": "dep_prop_propagation_engine", "target": "dep_prop_cycle_detection", "relation": "conceptually_related_to", "confidence": "EXTRACTED", "confidence_score": 1.0, "source_file": "docs/architecture/dependency-propagation.md", "source_location": "Cycle Detection section", "weight": 1.0}, {"source": "dep_prop_propagation_engine", "target": "dep_prop_batch_propagation", "relation": "conceptually_related_to", "confidence": "EXTRACTED", "confidence_score": 1.0, "source_file": "docs/architecture/dependency-propagation.md", "source_location": "Batch Propagation section", "weight": 1.0}, {"source": "dep_prop_propagation_engine", "target": "dep_prop_downstream_propagation", "relation": "conceptually_related_to", "confidence": "EXTRACTED", "confidence_score": 1.0, "source_file": "docs/architecture/dependency-propagation.md", "source_location": "Propagation Direction section", "weight": 1.0}, {"source": "dep_prop_propagation_engine", "target": "dep_prop_upstream_traversal", "relation": "conceptually_related_to", "confidence": "EXTRACTED", "confidence_score": 1.0, "source_file": "docs/architecture/dependency-propagation.md", "source_location": "Propagation Direction section", "weight": 1.0}, {"source": "dep_prop_propagation_engine", "target": "dep_prop_typed_edge_ref", "relation": "references", "confidence": "EXTRACTED", "confidence_score": 1.0, "source_file": "docs/architecture/dependency-propagation.md", "source_location": "Purpose section", "weight": 1.0}, {"source": "dep_prop_propagation_engine", "target": "dep_prop_adr004_ref", "relation": "references", "confidence": "EXTRACTED", "confidence_score": 1.0, "source_file": "docs/architecture/dependency-propagation.md", "source_location": "Propagation and Module Boundaries section", "weight": 1.0}, {"source": "dep_prop_invalidation_cascade", "target": "dep_prop_staleness", "relation": "conceptually_related_to", "confidence": "EXTRACTED", "confidence_score": 1.0, "source_file": "docs/architecture/dependency-propagation.md", "source_location": "Cascade Definition", "weight": 1.0}, {"source": "dep_prop_propagation_boundaries", "target": "dep_prop_invalidation_cascade", "relation": "conceptually_related_to", "confidence": "EXTRACTED", "confidence_score": 1.0, "source_file": "docs/architecture/dependency-propagation.md", "source_location": "Cascade Scope", "weight": 1.0}, {"source": "artifact_taxonomy_lifecycle", "target": "dep_prop_staleness", "relation": "semantically_similar_to", "confidence": "INFERRED", "confidence_score": 0.95, "source_file": "docs/architecture/dependency-propagation.md", "source_location": null, "weight": 1.0}, {"source": "phase4_node_states", "target": "dep_prop_staleness", "relation": "semantically_similar_to", "confidence": "INFERRED", "confidence_score": 0.95, "source_file": "docs/architecture/dependency-propagation.md", "source_location": null, "weight": 1.0}], "hyperedges": []}