{"nodes": [{"id": "c_users_user_dev_engraphsw_docs_domain_typed_edge_semantics_md", "label": "typed-edge-semantics.md", "file_type": "document", "source_file": "C:\\Users\\USER\\dev\\EngraphSW\\docs\\domain\\typed-edge-semantics.md", "source_location": "L1"}, {"id": "domain_typed_edge_semantics_typed_edge_semantics", "label": "Typed Edge Semantics", "file_type": "document", "source_file": "C:\\Users\\USER\\dev\\EngraphSW\\docs\\domain\\typed-edge-semantics.md", "source_location": "L1"}, {"id": "domain_typed_edge_semantics_purpose", "label": "Purpose", "file_type": "document", "source_file": "C:\\Users\\USER\\dev\\EngraphSW\\docs\\domain\\typed-edge-semantics.md", "source_location": "L3"}, {"id": "domain_typed_edge_semantics_edges_are_not_visual_connectors", "label": "Edges Are Not Visual Connectors", "file_type": "document", "source_file": "C:\\Users\\USER\\dev\\EngraphSW\\docs\\domain\\typed-edge-semantics.md", "source_location": "L19"}, {"id": "domain_typed_edge_semantics_edge_dimensions", "label": "Edge Dimensions", "file_type": "document", "source_file": "C:\\Users\\USER\\dev\\EngraphSW\\docs\\domain\\typed-edge-semantics.md", "source_location": "L39"}, {"id": "domain_typed_edge_semantics_edge_type_catalog", "label": "Edge Type Catalog", "file_type": "document", "source_file": "C:\\Users\\USER\\dev\\EngraphSW\\docs\\domain\\typed-edge-semantics.md", "source_location": "L55"}, {"id": "domain_typed_edge_semantics_derived_from", "label": "DERIVED_FROM", "file_type": "document", "source_file": "C:\\Users\\USER\\dev\\EngraphSW\\docs\\domain\\typed-edge-semantics.md", "source_location": "L59"}, {"id": "domain_typed_edge_semantics_refines", "label": "REFINES", "file_type": "document", "source_file": "C:\\Users\\USER\\dev\\EngraphSW\\docs\\domain\\typed-edge-semantics.md", "source_location": "L98"}, {"id": "domain_typed_edge_semantics_contextualizes", "label": "CONTEXTUALIZES", "file_type": "document", "source_file": "C:\\Users\\USER\\dev\\EngraphSW\\docs\\domain\\typed-edge-semantics.md", "source_location": "L133"}, {"id": "domain_typed_edge_semantics_influences", "label": "INFLUENCES", "file_type": "document", "source_file": "C:\\Users\\USER\\dev\\EngraphSW\\docs\\domain\\typed-edge-semantics.md", "source_location": "L171"}, {"id": "domain_typed_edge_semantics_implements", "label": "IMPLEMENTS", "file_type": "document", "source_file": "C:\\Users\\USER\\dev\\EngraphSW\\docs\\domain\\typed-edge-semantics.md", "source_location": "L208"}, {"id": "domain_typed_edge_semantics_contains", "label": "CONTAINS", "file_type": "document", "source_file": "C:\\Users\\USER\\dev\\EngraphSW\\docs\\domain\\typed-edge-semantics.md", "source_location": "L256"}, {"id": "domain_typed_edge_semantics_estimates", "label": "ESTIMATES", "file_type": "document", "source_file": "C:\\Users\\USER\\dev\\EngraphSW\\docs\\domain\\typed-edge-semantics.md", "source_location": "L305"}, {"id": "domain_typed_edge_semantics_exposes", "label": "EXPOSES", "file_type": "document", "source_file": "C:\\Users\\USER\\dev\\EngraphSW\\docs\\domain\\typed-edge-semantics.md", "source_location": "L344"}, {"id": "domain_typed_edge_semantics_impacts", "label": "IMPACTS", "file_type": "document", "source_file": "C:\\Users\\USER\\dev\\EngraphSW\\docs\\domain\\typed-edge-semantics.md", "source_location": "L381"}, {"id": "domain_typed_edge_semantics_mitigates", "label": "MITIGATES", "file_type": "document", "source_file": "C:\\Users\\USER\\dev\\EngraphSW\\docs\\domain\\typed-edge-semantics.md", "source_location": "L422"}, {"id": "domain_typed_edge_semantics_traces_to", "label": "TRACES_TO", "file_type": "document", "source_file": "C:\\Users\\USER\\dev\\EngraphSW\\docs\\domain\\typed-edge-semantics.md", "source_location": "L458"}, {"id": "domain_typed_edge_semantics_propagation_boundary_summary", "label": "Propagation Boundary Summary", "file_type": "document", "source_file": "C:\\Users\\USER\\dev\\EngraphSW\\docs\\domain\\typed-edge-semantics.md", "source_location": "L499"}, {"id": "domain_typed_edge_semantics_edge_validation_rules", "label": "Edge Validation Rules", "file_type": "document", "source_file": "C:\\Users\\USER\\dev\\EngraphSW\\docs\\domain\\typed-edge-semantics.md", "source_location": "L526"}, {"id": "domain_typed_edge_semantics_graph_integrity_constraints", "label": "Graph Integrity Constraints", "file_type": "document", "source_file": "C:\\Users\\USER\\dev\\EngraphSW\\docs\\domain\\typed-edge-semantics.md", "source_location": "L544"}, {"id": "domain_typed_edge_semantics_future_edge_types", "label": "Future Edge Types", "file_type": "document", "source_file": "C:\\Users\\USER\\dev\\EngraphSW\\docs\\domain\\typed-edge-semantics.md", "source_location": "L562"}], "edges": [{"source": "c_users_user_dev_engraphsw_docs_domain_typed_edge_semantics_md", "target": "domain_typed_edge_semantics_typed_edge_semantics", "relation": "contains", "confidence": "EXTRACTED", "source_file": "C:\\Users\\USER\\dev\\EngraphSW\\docs\\domain\\typed-edge-semantics.md", "source_location": "L1", "weight": 1.0}, {"source": "domain_typed_edge_semantics_typed_edge_semantics", "target": "domain_typed_edge_semantics_purpose", "relation": "contains", "confidence": "EXTRACTED", "source_file": "C:\\Users\\USER\\dev\\EngraphSW\\docs\\domain\\typed-edge-semantics.md", "source_location": "L3", "weight": 1.0}, {"source": "domain_typed_edge_semantics_typed_edge_semantics", "target": "domain_typed_edge_semantics_edges_are_not_visual_connectors", "relation": "contains", "confidence": "EXTRACTED", "source_file": "C:\\Users\\USER\\dev\\EngraphSW\\docs\\domain\\typed-edge-semantics.md", "source_location": "L19", "weight": 1.0}, {"source": "domain_typed_edge_semantics_typed_edge_semantics", "target": "domain_typed_edge_semantics_edge_dimensions", "relation": "contains", "confidence": "EXTRACTED", "source_file": "C:\\Users\\USER\\dev\\EngraphSW\\docs\\domain\\typed-edge-semantics.md", "source_location": "L39", "weight": 1.0}, {"source": "domain_typed_edge_semantics_typed_edge_semantics", "target": "domain_typed_edge_semantics_edge_type_catalog", "relation": "contains", "confidence": "EXTRACTED", "source_file": "C:\\Users\\USER\\dev\\EngraphSW\\docs\\domain\\typed-edge-semantics.md", "source_location": "L55", "weight": 1.0}, {"source": "domain_typed_edge_semantics_edge_type_catalog", "target": "domain_typed_edge_semantics_derived_from", "relation": "contains", "confidence": "EXTRACTED", "source_file": "C:\\Users\\USER\\dev\\EngraphSW\\docs\\domain\\typed-edge-semantics.md", "source_location": "L59", "weight": 1.0}, {"source": "domain_typed_edge_semantics_edge_type_catalog", "target": "domain_typed_edge_semantics_refines", "relation": "contains", "confidence": "EXTRACTED", "source_file": "C:\\Users\\USER\\dev\\EngraphSW\\docs\\domain\\typed-edge-semantics.md", "source_location": "L98", "weight": 1.0}, {"source": "domain_typed_edge_semantics_edge_type_catalog", "target": "domain_typed_edge_semantics_contextualizes", "relation": "contains", "confidence": "EXTRACTED", "source_file": "C:\\Users\\USER\\dev\\EngraphSW\\docs\\domain\\typed-edge-semantics.md", "source_location": "L133", "weight": 1.0}, {"source": "domain_typed_edge_semantics_edge_type_catalog", "target": "domain_typed_edge_semantics_influences", "relation": "contains", "confidence": "EXTRACTED", "source_file": "C:\\Users\\USER\\dev\\EngraphSW\\docs\\domain\\typed-edge-semantics.md", "source_location": "L171", "weight": 1.0}, {"source": "domain_typed_edge_semantics_edge_type_catalog", "target": "domain_typed_edge_semantics_implements", "relation": "contains", "confidence": "EXTRACTED", "source_file": "C:\\Users\\USER\\dev\\EngraphSW\\docs\\domain\\typed-edge-semantics.md", "source_location": "L208", "weight": 1.0}, {"source": "domain_typed_edge_semantics_edge_type_catalog", "target": "domain_typed_edge_semantics_contains", "relation": "contains", "confidence": "EXTRACTED", "source_file": "C:\\Users\\USER\\dev\\EngraphSW\\docs\\domain\\typed-edge-semantics.md", "source_location": "L256", "weight": 1.0}, {"source": "domain_typed_edge_semantics_edge_type_catalog", "target": "domain_typed_edge_semantics_estimates", "relation": "contains", "confidence": "EXTRACTED", "source_file": "C:\\Users\\USER\\dev\\EngraphSW\\docs\\domain\\typed-edge-semantics.md", "source_location": "L305", "weight": 1.0}, {"source": "domain_typed_edge_semantics_edge_type_catalog", "target": "domain_typed_edge_semantics_exposes", "relation": "contains", "confidence": "EXTRACTED", "source_file": "C:\\Users\\USER\\dev\\EngraphSW\\docs\\domain\\typed-edge-semantics.md", "source_location": "L344", "weight": 1.0}, {"source": "domain_typed_edge_semantics_edge_type_catalog", "target": "domain_typed_edge_semantics_impacts", "relation": "contains", "confidence": "EXTRACTED", "source_file": "C:\\Users\\USER\\dev\\EngraphSW\\docs\\domain\\typed-edge-semantics.md", "source_location": "L381", "weight": 1.0}, {"source": "domain_typed_edge_semantics_edge_type_catalog", "target": "domain_typed_edge_semantics_mitigates", "relation": "contains", "confidence": "EXTRACTED", "source_file": "C:\\Users\\USER\\dev\\EngraphSW\\docs\\domain\\typed-edge-semantics.md", "source_location": "L422", "weight": 1.0}, {"source": "domain_typed_edge_semantics_edge_type_catalog", "target": "domain_typed_edge_semantics_traces_to", "relation": "contains", "confidence": "EXTRACTED", "source_file": "C:\\Users\\USER\\dev\\EngraphSW\\docs\\domain\\typed-edge-semantics.md", "source_location": "L458", "weight": 1.0}, {"source": "domain_typed_edge_semantics_typed_edge_semantics", "target": "domain_typed_edge_semantics_propagation_boundary_summary", "relation": "contains", "confidence": "EXTRACTED", "source_file": "C:\\Users\\USER\\dev\\EngraphSW\\docs\\domain\\typed-edge-semantics.md", "source_location": "L499", "weight": 1.0}, {"source": "domain_typed_edge_semantics_typed_edge_semantics", "target": "domain_typed_edge_semantics_edge_validation_rules", "relation": "contains", "confidence": "EXTRACTED", "source_file": "C:\\Users\\USER\\dev\\EngraphSW\\docs\\domain\\typed-edge-semantics.md", "source_location": "L526", "weight": 1.0}, {"source": "domain_typed_edge_semantics_typed_edge_semantics", "target": "domain_typed_edge_semantics_graph_integrity_constraints", "relation": "contains", "confidence": "EXTRACTED", "source_file": "C:\\Users\\USER\\dev\\EngraphSW\\docs\\domain\\typed-edge-semantics.md", "source_location": "L544", "weight": 1.0}, {"source": "domain_typed_edge_semantics_typed_edge_semantics", "target": "domain_typed_edge_semantics_future_edge_types", "relation": "contains", "confidence": "EXTRACTED", "source_file": "C:\\Users\\USER\\dev\\EngraphSW\\docs\\domain\\typed-edge-semantics.md", "source_location": "L562", "weight": 1.0}], "input_tokens": 0, "output_tokens": 0}